PySoundSphere/__init__.py
PySoundSphere/main.py
PySoundSphere/playback_backend/backend_loader.py
PySoundSphere/playback_backend/ffplay_backend.py
PySoundSphere/playback_backend/pygame_backend.py
PySoundSphere/playback_backend/sounddevice_backend.py
pysoundsphere-0.0.8.dist-info/METADATA
pysoundsphere-0.0.8.dist-info/WHEEL
pysoundsphere-0.0.8.dist-info/licenses/LICENSE.md
pysoundsphere-0.0.8.dist-info/RECORD
