Metadata-Version: 2.3
Name: PySoundSphere
Version: 0.0.8
Summary: Play Audio Using Python
Project-URL: Source, https://github.com/Nmstr/PySoundSphere
Project-URL: Documentation, https://nmstr.github.io/PySoundSphere/
Project-URL: Issues, https://github.com/Nmstr/PySoundSphere/issues
Author-email: "Namester (Nmstr)" <publicNamester@gmail.com>
License-File: LICENSE.md
Keywords: audio,playback,sound
Classifier: Intended Audience :: Developers
Classifier: License :: OSI Approved :: GNU General Public License v3 (GPLv3)
Classifier: Programming Language :: Python :: 3
Classifier: Topic :: Multimedia :: Sound/Audio
Classifier: Topic :: Multimedia :: Sound/Audio :: Players
Classifier: Topic :: Software Development :: Libraries
Classifier: Topic :: Utilities
Requires-Python: >=3.8
Provides-Extra: pygame-backend
Requires-Dist: pygame; extra == 'pygame-backend'
Provides-Extra: sounddevice-backend
Requires-Dist: numpy; extra == 'sounddevice-backend'
Requires-Dist: sounddevice; extra == 'sounddevice-backend'
Requires-Dist: soundfile; extra == 'sounddevice-backend'
